[
  {
    "numero": "TASK0948949", 
    "aberto": "29/04/2024 11:15:10", 
    "atualizado_em": "03/05/2024 13:43:13", 
    "estado_relatorio": "Resolvido", 
    "resolvido_relatorio": "03/05/2024", 
    "categoria_relatorio": "Equipamento de TI", 
    "subcategoria_relatorio": "Hands on", 
    "sintoma": "Hands on", 
    "qualificacao_sintoma": "", 
    "grupo_de_atribuicao": "N2-FS-NA", 
    "categoria": "Ativos", 
    "atribuido_a": "Analista Service Desk", 
    "prioridade": "3 - Baixo", 
    "encerrado": "03/05/2024 13:43:14", 
    "solicitante_tarefa": "ADM Sistemas", 
    "local": "Fábrica 1", 
    "descricao": "Solicito novo ponto de rede", 
    "comentarios_visiveis_pergunta": "Informar local e aval para criação ponto de rede", 
    "comentarios_visiveis_resposta": "Aguardando passagem do cabeamento", 
    "resolucao": "Pontos criados e ativados"
  },
  {
    "numero": "TASK0950427", 
    "aberto": "02/05/2024 05:37:17", 
    "atualizado_em": "03/05/2024 00:34:26", 
    "estado_relatorio": "Resolvido", 
    "resolvido_relatorio": "03/05/2024", 
    "categoria_relatorio": "Serviços de TI", 
    "subcategoria_relatorio": "Infraestrutura - Soluções", 
    "sintoma": "Instalação de Aplicativos", 
    "qualificacao_sintoma": "Suporte a Instalação e Configuração de Aplicativos", 
    "grupo_de_atribuicao": "N2-FS-NA", 
    "categoria": "Field Service", 
    "atribuido_a": "Analista Field", 
    "prioridade": "3 - Baixo", 
    "encerrado": "03/05/2024 00:34:26", 
    "solicitante_tarefa": "ADM Sistemas", 
    "local": "Fábrica 1", 
    "descricao": "Solicito novo ponto de rede", 
    "comentarios_visiveis_pergunta": "Informar local e aval para criação ponto de rede", 
    "comentarios_visiveis_resposta": "Aguardando passagem do cabeamento", 
    "resolucao": "Pontos criados e ativados"
  },
  {
    "numero": "TASK0950560", 
    "aberto": "02/05/2024 09:02:47", 
    "atualizado_em": "02/05/2024 15:13:57", 
    "estado_relatorio": "Resolvido", 
    "resolvido_relatorio": "02/05/2024", 
    "categoria_relatorio": "Equipamento de TI", 
    "subcategoria_relatorio": "Controle de Acesso e Relógio de Ponto", 
    "sintoma": "Suporte", 
    "qualificacao_sintoma": "Porta", 
    "grupo_de_atribuicao": "N2-FS-NA", 
    "categoria": "Field Service", 
    "atribuido_a": "Analista Field", 
    "prioridade": "3 - Baixo", 
    "encerrado": "02/05/2024 15:13:57", 
    "solicitante_tarefa": "ADM Sistemas", 
    "local": "Escritório central", 
    "descricao": "Controle de Acesso e Relógio de Ponto", 
    "comentarios_visiveis_pergunta": "Porta lenta ao abrir", 
    "comentarios_visiveis_resposta": "Por favor informar local ", 
    "resolucao": "Realizado restart do serviço local "
  },
  {
    "numero": "TASK0950674", 
    "aberto": "02/05/2024 09:43:30", 
    "atualizado_em": "02/05/2024 13:03:35", 
    "estado_relatorio": "Resolvido", 
    "resolvido_relatorio": "02/05/2024", 
    "categoria_relatorio": "Equipamento de TI", 
    "subcategoria_relatorio": "Controle de Acesso e Relógio de Ponto", 
    "sintoma": "Suporte", 
    "qualificacao_sintoma": "REP", 
    "grupo_de_atribuicao": "N2-FS-NA", 
    "categoria": "Field Service", 
    "atribuido_a": "Analista Field", 
    "prioridade": "3 - Baixo", 
    "encerrado": "02/05/2024 13:03:35", 
    "solicitante_tarefa": "ADM Sistemas", 
    "local": "Centro de Distribuição", 
    "descricao": "Controle de Acesso e Relógio de Ponto", 
    "comentarios_visiveis_pergunta": "Porta lenta ao abrir", 
    "comentarios_visiveis_resposta": "Por favor informar local ", 
    "resolucao": "Realizado restart do serviço local "
  },
  {
    "numero": "TASK0950875", 
    "aberto": "02/05/2024 11:33:41", 
    "atualizado_em": "02/05/2024 16:30:38", 
    "estado_relatorio": "Fechado", 
    "resolvido_relatorio": "02/05/2024", 
    "categoria_relatorio": "Outros Sistemas", 
    "subcategoria_relatorio": "DocNix", 
    "sintoma": "Outros", 
    "qualificacao_sintoma": "", 
    "grupo_de_atribuicao": "N2-LEG-SAT", 
    "categoria": "AMS-Não SAP", 
    "atribuido_a": "Analista AMS", 
    "prioridade": "3 - Baixo", 
    "encerrado": "02/05/2024 16:30:36", 
    "solicitante_tarefa": "ADM Sistemas", 
    "local": "Fábrica 1", 
    "descricao": "Sistema lento", 
    "comentarios_visiveis_pergunta": "Somente em sua maquina ?", 
    "comentarios_visiveis_resposta": "Somente na minha maquina", 
    "resolucao": "Solução aplicada Reinciado sistema operacional local "
  },
  {
    "numero": "TASK0951510", 
    "aberto": "03/05/2024 08:37:13", 
    "atualizado_em": "03/05/2024 09:57:23", 
    "estado_relatorio": "Resolvido", 
    "resolvido_relatorio": "03/05/2024", 
    "categoria_relatorio": "Outros Sistemas", 
    "subcategoria_relatorio": "Dynamics", 
    "sintoma": "Auditoria Interna", 
    "qualificacao_sintoma": "Outros", 
    "grupo_de_atribuicao": "N2-LEG-SAT", 
    "categoria": "AMS-Não SAP", 
    "atribuido_a": "Analista AMS", 
    "prioridade": "3 - Baixo", 
    "encerrado": "03/05/2024 09:57:23", 
    "solicitante_tarefa": "ADM Sistemas", 
    "local": "Centro de Distribuição", 
    "descricao": "Sistema lento", 
    "comentarios_visiveis_pergunta": "Somente em sua maquina ?", 
    "comentarios_visiveis_resposta": "Somente na minha maquina", 
    "resolucao": "Solução aplicada Reinciado sistema operacional local "
  },
  {
    "numero": "TASK0951667", 
    "aberto": "03/05/2024 09:44:47", 
    "atualizado_em": "03/05/2024 09:49:36", 
    "estado_relatorio": "Resolvido", 
    "resolvido_relatorio": "03/05/2024", 
    "categoria_relatorio": "Equipamento de TI", 
    "subcategoria_relatorio": "Hands on", 
    "sintoma": "Ativar Ponto de Rede", 
    "qualificacao_sintoma": "", 
    "grupo_de_atribuicao": "N2-FS-NA", 
    "categoria": "Field Service", 
    "atribuido_a": "Analista Field", 
    "prioridade": "3 - Baixo", 
    "encerrado": "03/05/2024 09:49:36", 
    "solicitante_tarefa": "ADM Sistemas", 
    "local": "Escritório central", 
    "descricao": "Sistema lento", 
    "comentarios_visiveis_pergunta": "Somente em sua maquina ?", 
    "comentarios_visiveis_resposta": "Somente na minha maquina", 
    "resolucao": "Solução aplicada Reinciado sistema operacional local "
  },
  {
    "numero": "TASK0951715", 
    "aberto": "03/05/2024 10:04:45", 
    "atualizado_em": "03/05/2024 17:17:11", 
    "estado_relatorio": "Resolvido", 
    "resolvido_relatorio": "03/05/2024", 
    "categoria_relatorio": "Outros Sistemas", 
    "subcategoria_relatorio": "HCA", 
    "sintoma": "Dúvida", 
    "qualificacao_sintoma": "Informação", 
    "grupo_de_atribuicao": "N2-LEG-SAT", 
    "categoria": "AMS-Não SAP", 
    "atribuido_a": "Analista AMS", 
    "prioridade": "3 - Baixo", 
    "encerrado": "03/05/2024 17:17:11", 
    "solicitante_tarefa": "ADM Sistemas", 
    "local": "Escritório central", 
    "descricao": "Sistema lento", 
    "comentarios_visiveis_pergunta": "Somente em sua maquina ?", 
    "comentarios_visiveis_resposta": "Em todo departamento", 
    "resolucao": "Solução aplicada Reinciado serviço database"
  },
  {
    "numero": "TASK0951951", 
    "aberto": "03/05/2024 12:55:09", 
    "atualizado_em": "03/05/2024 13:18:47", 
    "estado_relatorio": "Resolvido", 
    "resolvido_relatorio": "03/05/2024", 
    "categoria_relatorio": "Equipamento de TI", 
    "subcategoria_relatorio": "Hands on", 
    "sintoma": "Solicitação de NF Entrada\\Saída", 
    "qualificacao_sintoma": "", 
    "grupo_de_atribuicao": "N2-AT-EXTERNOS", 
    "categoria": "Ativos", 
    "atribuido_a": "Analista Service Desk", 
    "prioridade": "3 - Baixo", 
    "encerrado": "03/05/2024 12:59:36", 
    "solicitante_tarefa": "ADM Sistemas", 
    "local": "Centro de Distribuição", 
    "descricao": "Sistema lento", 
    "comentarios_visiveis_pergunta": "Somente em sua maquina ?", 
    "comentarios_visiveis_resposta": "Em todo departamento", 
    "resolucao": "Solução aplicada Reinciado serviço database"
  },
  {
    "numero": "TASK0951957", 
    "aberto": "03/05/2024 13:02:51", 
    "atualizado_em": "03/05/2024 13:18:29", 
    "estado_relatorio": "Resolvido", 
    "resolvido_relatorio": "03/05/2024", 
    "categoria_relatorio": "Equipamento de TI", 
    "subcategoria_relatorio": "Hands on", 
    "sintoma": "Solicitação de NF Entrada\\Saída", 
    "qualificacao_sintoma": "", 
    "grupo_de_atribuicao": "N2-AT-EXTERNOS", 
    "categoria": "Ativos", 
    "atribuido_a": "Analista Service Desk", 
    "prioridade": "3 - Baixo", 
    "encerrado": "03/05/2024 13:06:37", 
    "solicitante_tarefa": "ADM Sistemas", 
    "local": "Centro de Distribuição", 
    "descricao": "Sistema lento", 
    "comentarios_visiveis_pergunta": "Somente em sua maquina ?", 
    "comentarios_visiveis_resposta": "Em todo departamento", 
    "resolucao": "Solução aplicada Reinciado serviço database"
  },
  {
    "numero": "TASK0951959", 
    "aberto": "03/05/2024 13:06:27", 
    "atualizado_em": "03/05/2024 13:34:03", 
    "estado_relatorio": "Resolvido", 
    "resolvido_relatorio": "03/05/2024", 
    "categoria_relatorio": "Impressoras", 
    "subcategoria_relatorio": "Suporte Impressoras", 
    "sintoma": "Troca de Toner", 
    "qualificacao_sintoma": "", 
    "grupo_de_atribuicao": "N2-FS-NA", 
    "categoria": "Field Service", 
    "atribuido_a": "Analista Field", 
    "prioridade": "3 - Baixo", 
    "encerrado": "03/05/2024 13:34:03", 
    "solicitante_tarefa": "ADM Sistemas", 
    "local": "Centro de Distribuição", 
    "descricao": "Suporte Impressoras", 
    "comentarios_visiveis_pergunta": "Papel atolado", 
    "comentarios_visiveis_resposta": "informar local da impressora?", 
    "resolucao": "Realizado a retirada dos papeis atolados"
  },
  {
    "numero": "TASK0951964", 
    "aberto": "03/05/2024 13:15:34", 
    "atualizado_em": "03/05/2024 13:18:10", 
    "estado_relatorio": "Resolvido", 
    "resolvido_relatorio": "03/05/2024", 
    "categoria_relatorio": "Equipamento de TI", 
    "subcategoria_relatorio": "Hands on", 
    "sintoma": "Solicitação de NF Entrada\\Saída", 
    "qualificacao_sintoma": "", 
    "grupo_de_atribuicao": "N2-AT-EXTERNOS", 
    "categoria": "Ativos", 
    "atribuido_a": "Analista Service Desk", 
    "prioridade": "3 - Baixo", 
    "encerrado": "03/05/2024 13:18:10", 
    "solicitante_tarefa": "ADM Sistemas", 
    "local": "Centro de Distribuição", 
    "descricao": "Configuração de Equipamento", 
    "comentarios_visiveis_pergunta": "Configurar Smartphone XXXX", 
    "comentarios_visiveis_resposta": "informar melhor horário para atendimento ", 
    "resolucao": "Realizado a configuração do smartphone conforme solicitado"
  },
  {
    "numero": "TASK0951989", 
    "aberto": "03/05/2024 13:51:37", 
    "atualizado_em": "03/05/2024 13:53:26", 
    "estado_relatorio": "Resolvido", 
    "resolvido_relatorio": "03/05/2024", 
    "categoria_relatorio": "Equipamento de TI", 
    "subcategoria_relatorio": "Hands on", 
    "sintoma": "Transferência de Equipamento", 
    "qualificacao_sintoma": "", 
    "grupo_de_atribuicao": "N2-FS-NA", 
    "categoria": "Ativos", 
    "atribuido_a": "Analista Service Desk", 
    "prioridade": "3 - Baixo", 
    "encerrado": "03/05/2024 13:53:26", 
    "solicitante_tarefa": "ADM Sistemas", 
    "local": "Centro de Distribuição", 
    "descricao": "Transferência de Equipamento", 
    "comentarios_visiveis_pergunta": "Informar numero da nota de entrada", 
    "comentarios_visiveis_resposta": "Informação anxeada conforme solicitado", 
    "resolucao": "Nota de saida anexada e enviada para seguir com transferencia"
  },
  {
    "numero": "TASK0952138", 
    "aberto": "03/05/2024 15:52:12", 
    "atualizado_em": "03/05/2024 16:26:54", 
    "estado_relatorio": "Resolvido", 
    "resolvido_relatorio": "03/05/2024", 
    "categoria_relatorio": "Suporte a Equipamento", 
    "subcategoria_relatorio": "Roaming Internacional", 
    "sintoma": "Liberação de Roaming Internacional", 
    "qualificacao_sintoma": "", 
    "grupo_de_atribuicao": "TELEFONIA", 
    "categoria": "Field Service", 
    "atribuido_a": "Analista Field", 
    "prioridade": "3 - Baixo", 
    "encerrado": "03/05/2024 16:26:54", 
    "solicitante_tarefa": "ADM Sistemas", 
    "local": "Centro de Distribuição", 
    "descricao": "Roaming Internacional", 
    "comentarios_visiveis_pergunta": "Informar data para ativação ", 
    "comentarios_visiveis_resposta": "Data informadas conforme solicitado", 
    "resolucao": "Ativação do Roaming Internacional concluida conforme solicitado"
  }
]